sfttoolbox/__init__.py
sfttoolbox/graphing.py
sfttoolbox/DES/__init__.py
sfttoolbox/DES/_des.py
sfttoolbox/DES/examples/__init__.py
sfttoolbox/DES/examples/_example1.py
sfttoolbox/DES/examples/_example2.py
sfttoolbox/mapping/__init__.py
sfttoolbox/mapping/isochrone_generator.py
sfttoolbox/mapping/examples/__init__.py
sfttoolbox/mapping/examples/example1.py
sfttoolbox/mapping/examples/example2.py
sfttoolbox/plotting/__init__.py
sfttoolbox/plotting/_plotting.py
sfttoolbox-1.0.1.dist-info/licenses/LICENSE.txt
test/__init__.py
test/DES/__init__.py
test/DES/test_des.py
test/mapping/__init__.py
test/mapping/test_isochrone_generator.py
test/mapping/test_somerset_map.py
sfttoolbox-1.0.1.dist-info/METADATA
sfttoolbox-1.0.1.dist-info/WHEEL
sfttoolbox-1.0.1.dist-info/top_level.txt
sfttoolbox-1.0.1.dist-info/RECORD
