Metadata-Version: 2.4
Name: sfttoolbox
Version: 1.0.1
Summary: Useful tools for sft data science
Author-email: Chris Sampson <christopher.sampson@somersetft.nhs.uk>, Sam Vautier <samantha.vautier@somersetft.nhs.uk>, Jawad Iqbal <jawad.iqbal@somersetft.nhs.uk>
Project-URL: Homepage, https://github.com/SomersetNHSFoundationTrust/sfttoolbox
Project-URL: Issues, https://github.com/SomersetNHSFoundationTrust/sfttoolbox/issues
Classifier: Programming Language :: Python :: 3
Classifier: Operating System :: OS Independent
Requires-Python: >=3.8
License-File: LICENSE.txt
Requires-Dist: plotly>=5.19
Requires-Dist: pyvis
Requires-Dist: folium
Requires-Dist: geopandas
Requires-Dist: shapely
Requires-Dist: networkx
Requires-Dist: numpy
Requires-Dist: osmnx
Requires-Dist: alphashape
Dynamic: license-file
